{"frames": [

{
	"filename": "badges/bronze.png",
	"frame": {"x":1641,"y":517,"w":77,"h":81},
	"rotated": false,
	"trimmed": true,
	"spriteSourceSize": {"x":0,"y":1,"w":77,"h":81},
	"sourceSize": {"w":77,"h":82}
},
{
	"filename": "badges/diamond.png",
	"frame": {"x":1641,"y":600,"w":77,"h":81},
	"rotated": false,
	"trimmed": true,
	"spriteSourceSize": {"x":0,"y":1,"w":77,"h":81},
	"sourceSize": {"w":77,"h":82}
},
{
	"filename": "badges/gold.png",
	"frame": {"x":781,"y":958,"w":77,"h":81},
	"rotated": false,
	"trimmed": true,
	"spriteSourceSize": {"x":0,"y":1,"w":77,"h":81},
	"sourceSize": {"w":77,"h":82}
},
{
	"filename": "badges/silver.png",
	"frame": {"x":781,"y":1041,"w":77,"h":81},
	"rotated": false,
	"trimmed": true,
	"spriteSourceSize": {"x":0,"y":1,"w":77,"h":81},
	"sourceSize": {"w":77,"h":82}
},
{
	"filename": "dailyChallenges/coins.png",
	"frame": {"x":569,"y":855,"w":276,"h":101},
	"rotated": false,
	"trimmed": false,
	"spriteSourceSize": {"x":0,"y":0,"w":276,"h":101},
	"sourceSize": {"w":276,"h":101}
},
{
	"filename": "dailyChallenges/dailyChallenges.png",
	"frame": {"x":1,"y":1,"w":862,"h":336},
	"rotated": false,
	"trimmed": false,
	"spriteSourceSize": {"x":0,"y":0,"w":862,"h":336},
	"sourceSize": {"w":862,"h":336}
},
{
	"filename": "dailyChallenges/logo.png",
	"frame": {"x":860,"y":1065,"w":48,"h":54},
	"rotated": false,
	"trimmed": false,
	"spriteSourceSize": {"x":0,"y":0,"w":48,"h":54},
	"sourceSize": {"w":48,"h":54}
},
{
	"filename": "more/awards-and-achievements.png",
	"frame": {"x":1,"y":855,"w":566,"h":272},
	"rotated": false,
	"trimmed": false,
	"spriteSourceSize": {"x":0,"y":0,"w":566,"h":272},
	"sourceSize": {"w":566,"h":272}
},
{
	"filename": "more/awards-and-achievments.png",
	"frame": {"x":1,"y":855,"w":566,"h":272},
	"rotated": false,
	"trimmed": false,
	"spriteSourceSize": {"x":0,"y":0,"w":566,"h":272},
	"sourceSize": {"w":566,"h":272}
},
{
	"filename": "more/how-to-play.png",
	"frame": {"x":865,"y":517,"w":566,"h":272},
	"rotated": false,
	"trimmed": false,
	"spriteSourceSize": {"x":0,"y":0,"w":566,"h":272},
	"sourceSize": {"w":566,"h":272}
},
{
	"filename": "more/statistics.png",
	"frame": {"x":865,"y":791,"w":566,"h":272},
	"rotated": false,
	"trimmed": false,
	"spriteSourceSize": {"x":0,"y":0,"w":566,"h":272},
	"sourceSize": {"w":566,"h":272}
},
{
	"filename": "previewBig/theme1_preview_big.png",
	"frame": {"x":1,"y":339,"w":862,"h":256},
	"rotated": false,
	"trimmed": false,
	"spriteSourceSize": {"x":0,"y":0,"w":862,"h":256},
	"sourceSize": {"w":862,"h":256}
},
{
	"filename": "previewBig/theme2_preview_big.png",
	"frame": {"x":865,"y":1,"w":862,"h":256},
	"rotated": false,
	"trimmed": false,
	"spriteSourceSize": {"x":0,"y":0,"w":862,"h":256},
	"sourceSize": {"w":862,"h":256}
},
{
	"filename": "previewBig/theme3_preview_big.png",
	"frame": {"x":1,"y":597,"w":862,"h":256},
	"rotated": false,
	"trimmed": false,
	"spriteSourceSize": {"x":0,"y":0,"w":862,"h":256},
	"sourceSize": {"w":862,"h":256}
},
{
	"filename": "previewBig/theme4_preview_big.png",
	"frame": {"x":865,"y":259,"w":862,"h":256},
	"rotated": false,
	"trimmed": false,
	"spriteSourceSize": {"x":0,"y":0,"w":862,"h":256},
	"sourceSize": {"w":862,"h":256}
},
{
	"filename": "puzzle/logo.png",
	"frame": {"x":910,"y":1065,"w":36,"h":54},
	"rotated": false,
	"trimmed": false,
	"spriteSourceSize": {"x":0,"y":0,"w":36,"h":54},
	"sourceSize": {"w":36,"h":54}
},
{
	"filename": "recentlyPlayed/green-4.png",
	"frame": {"x":569,"y":958,"w":210,"h":136},
	"rotated": false,
	"trimmed": false,
	"spriteSourceSize": {"x":0,"y":0,"w":210,"h":136},
	"sourceSize": {"w":210,"h":136}
},
{
	"filename": "recentlyPlayed/purple-4.png",
	"frame": {"x":1433,"y":717,"w":210,"h":136},
	"rotated": false,
	"trimmed": false,
	"spriteSourceSize": {"x":0,"y":0,"w":210,"h":136},
	"sourceSize": {"w":210,"h":136}
},
{
	"filename": "recentlyPlayed/red-4.png",
	"frame": {"x":1433,"y":855,"w":210,"h":136},
	"rotated": false,
	"trimmed": false,
	"spriteSourceSize": {"x":0,"y":0,"w":210,"h":136},
	"sourceSize": {"w":210,"h":136}
},
{
	"filename": "recentlyPlayed/yellow-4.png",
	"frame": {"x":1433,"y":993,"w":210,"h":136},
	"rotated": false,
	"trimmed": false,
	"spriteSourceSize": {"x":0,"y":0,"w":210,"h":136},
	"sourceSize": {"w":210,"h":136}
},
{
	"filename": "theme/check-mark.png",
	"frame": {"x":1433,"y":517,"w":206,"h":198},
	"rotated": false,
	"trimmed": false,
	"spriteSourceSize": {"x":0,"y":0,"w":206,"h":198},
	"sourceSize": {"w":206,"h":198}
},
{
	"filename": "theme/frame-highlight-corner.png",
	"frame": {"x":1,"y":1129,"w":10,"h":10},
	"rotated": false,
	"trimmed": false,
	"spriteSourceSize": {"x":0,"y":0,"w":10,"h":10},
	"sourceSize": {"w":10,"h":10}
},
{
	"filename": "theme/frame-highlight.png",
	"frame": {"x":1641,"y":683,"w":10,"h":10},
	"rotated": false,
	"trimmed": false,
	"spriteSourceSize": {"x":0,"y":0,"w":10,"h":10},
	"sourceSize": {"w":10,"h":10}
}],
"meta": {
	"app": "http://www.codeandweb.com/texturepacker",
	"version": "1.0",
	"image": "home-state.png",
	"format": "RGBA8888",
	"size": {"w":1728,"h":1140},
	"scale": "1",
	"smartupdate": "$TexturePacker:SmartUpdate:c7888df93d232c2a3645d932ba628da0:0787bddb6cf8cc016085c12f350e2fba:11e2fb1cbe62502a7b167261f0660c1d$"
}
}
